odoo/addons/test_base_import_pdf_by_template/README.rst
odoo/addons/test_base_import_pdf_by_template/__init__.py
odoo/addons/test_base_import_pdf_by_template/__manifest__.py
odoo/addons/test_base_import_pdf_by_template/hooks.py
odoo/addons/test_base_import_pdf_by_template/demo/base_import_pdf_template.xml
odoo/addons/test_base_import_pdf_by_template/i18n/it.po
odoo/addons/test_base_import_pdf_by_template/i18n/test_base_import_pdf_by_template.pot
odoo/addons/test_base_import_pdf_by_template/readme/CONTRIBUTORS.md
odoo/addons/test_base_import_pdf_by_template/readme/DESCRIPTION.md
odoo/addons/test_base_import_pdf_by_template/static/description/icon.png
odoo/addons/test_base_import_pdf_by_template/static/description/index.html
odoo/addons/test_base_import_pdf_by_template/tests/__init__.py
odoo/addons/test_base_import_pdf_by_template/tests/test_base_import_pdf_by_template.py
odoo/addons/test_base_import_pdf_by_template/tests/data/purchase_order_declathon.pdf
odoo_addon_test_base_import_pdf_by_template-17.0.1.1.2.1.dist-info/METADATA
odoo_addon_test_base_import_pdf_by_template-17.0.1.1.2.1.dist-info/WHEEL
odoo_addon_test_base_import_pdf_by_template-17.0.1.1.2.1.dist-info/top_level.txt
odoo_addon_test_base_import_pdf_by_template-17.0.1.1.2.1.dist-info/RECORD
